{
  "extras": [
    "lazyvim.plugins.extras.editor.inc-rename",
    "lazyvim.plugins.extras.formatting.biome",
    "lazyvim.plugins.extras.lang.astro",
    "lazyvim.plugins.extras.lang.docker",
    "lazyvim.plugins.extras.lang.java",
    "lazyvim.plugins.extras.lang.json",
    "lazyvim.plugins.extras.lang.kotlin",
    "lazyvim.plugins.extras.lang.markdown",
    "lazyvim.plugins.extras.lang.typescript",
    "lazyvim.plugins.extras.linting.eslint"
  ],
  "install_version": 8,
  "news": {
    "NEWS.md": "10960"
  },
  "version": 8
}